{
  "version": 1,
  "items": [
    {
      "name": " Toyota  Camry Элеганс safety",
      "specs": [
        {
          "name": "name",
          "value": " Toyota  Camry Элеганс safety",
          "weight": 1
        },
        {
          "name": "цена",
          "value": "28 430",
          "weight": 1
        },
        {
          "name": "Расход",
          "value": "11 / 5.9",
          "weight": 1
        },
        {
          "name": "Объём",
          "value": "2,5(181)",
          "weight": 1
        },
        {
          "name": "КПП",
          "value": "6АТ",
          "weight": 1
        },
        {
          "name": "Привод",
          "value": "Передний",
          "weight": 1
        },
        {
          "name": "Длина",
          "value": "4850",
          "weight": 1
        },
        {
          "name": "Фары",
          "value": " светодиодные\t\nс автоматическим управлением дальним светом",
          "weight": 1
        },
        {
          "name": "Диски",
          "value": "R17 легкосплавные",
          "weight": 1
        },
        {
          "name": "Безключевой доступ",
          "value": "Система дистанционной \nидентификации ключей",
          "weight": 1
        },
        {
          "name": "Запуск двигателя с кнопки",
          "value": "да",
          "weight": 1
        },
        {
          "name": "Подушки безопасности",
          "value": "фронтальные  (2)\nбоковые  (2)\nбоковые шторки  (4)\nколенные  (1)",
          "weight": 1
        },
        {
          "name": "Круиз-контроль  ",
          "value": "адаптивный",
          "weight": 1
        },
        {
          "name": "Климат",
          "value": "двухзонный",
          "weight": 1
        },
        {
          "name": "камера заднего вида ",
          "value": "задняя",
          "weight": 1
        },
        {
          "name": " обивка сидений ",
          "value": "кожей",
          "weight": 1
        },
        {
          "name": "Регулировка сиденья водителя  ",
          "value": "\t\nегулировка поясничного подпора\nсидений водителя и пассажира с электроприводом\nЭлектропривод\t\nсиденья водителя\nсиденья переднего пассажира",
          "weight": 1
        },
        {
          "name": "подогрев передних сидений, \n",
          "value": "да",
          "weight": 1
        },
        {
          "name": "Подогрев рулевого колеса\n",
          "value": "да",
          "weight": 1
        },
        {
          "name": "подогрев задних сидений",
          "value": "да",
          "weight": 1
        },
        {
          "name": "Подогрев лобового стекла ",
          "value": "с обогревом\t\nс обогревом форсунок стеклоомывателя",
          "weight": 1
        },
        {
          "name": "Дисплей передний\t",
          "value": "да",
          "weight": 1
        },
        {
          "name": "Навигационная система 7',",
          "value": "нет",
          "weight": 1
        }
      ]
    },
    {
      "name": "Ford Mondeo V Titanium",
      "specs": [
        {
          "name": "name",
          "value": "Ford Mondeo V Titanium",
          "weight": 1
        },
        {
          "name": "цена",
          "value": "27990",
          "weight": 1
        },
        {
          "name": "Расход",
          "value": "10.7 / 6",
          "weight": 1
        },
        {
          "name": "Объём",
          "value": "2.0 (199)",
          "weight": 1
        },
        {
          "name": "КПП",
          "value": "6АТ",
          "weight": 1
        },
        {
          "name": "Привод",
          "value": "Передний",
          "weight": 1
        },
        {
          "name": "Длина",
          "value": "4850",
          "weight": 1
        },
        {
          "name": "Фары",
          "value": "галогеновые\nс автоматическим управлением дальним светом",
          "weight": 1
        }
      ]
    },
    {
      "name": "RAV-4 Комфорт плюс",
      "specs": [
        {
          "name": "name",
          "value": "RAV-4 Комфорт плюс",
          "weight": 1
        },
        {
          "name": "цена",
          "value": "26 895 ",
          "weight": 1
        },
        {
          "name": "Расход",
          "value": "9,4 /6,3",
          "weight": 1
        },
        {
          "name": "Объём",
          "value": "2,0 (146)",
          "weight": 1
        },
        {
          "name": "КПП",
          "value": "Вариатор",
          "weight": 1
        },
        {
          "name": "Привод",
          "value": "Полный подключаемый",
          "weight": 1
        },
        {
          "name": "Длина",
          "value": "4605",
          "weight": 1
        },
        {
          "name": "Фары",
          "value": "светодиодные",
          "weight": 1
        },
        {
          "name": "Диски",
          "value": "стальные 17'",
          "weight": 1
        },
        {
          "name": "Безключевой доступ",
          "value": "Система дистанционной \nидентификации ключей",
          "weight": 1
        },
        {
          "name": "Запуск двигателя с кнопки",
          "value": "да",
          "weight": 1
        },
        {
          "name": "Подушки безопасности",
          "value": "фронтальные  (2)        \nбоковые  (2)        \nбоковые шторки  (4)\nколенные \nПреднатяжители ремней",
          "weight": 1
        },
        {
          "name": "Круиз-контроль  ",
          "value": "да",
          "weight": 1
        },
        {
          "name": "Климат",
          "value": "двухзонный",
          "weight": 1
        },
        {
          "name": "камера заднего вида ",
          "value": "задняя",
          "weight": 1
        },
        {
          "name": "-контроля давления воздуха в шинах (TMPS)        ",
          "value": "да",
          "weight": 1
        },
        {
          "name": " обивка сидений ",
          "value": "тканью",
          "weight": 1
        },
        {
          "name": "Регулировка сиденья водителя  ",
          "value": "по высоте механическая",
          "weight": 1
        },
        {
          "name": "подогрев передних сидений, \n",
          "value": "да",
          "weight": 1
        },
        {
          "name": "Подогрев рулевого колеса\n",
          "value": "да",
          "weight": 1
        },
        {
          "name": "подогрев задних сидений",
          "value": "нет",
          "weight": 1
        },
        {
          "name": "Подогрев лобового стекла ",
          "value": "с обогревом\t\nс обогревом в зоне стоянки стеклоочистителей\n\tс обогревом форсунок стеклоомы",
          "weight": 1
        },
        {
          "name": "Дисплей передний\t",
          "value": "да",
          "weight": 1
        },
        {
          "name": "Навигационная система 7',",
          "value": "нет",
          "weight": 1
        },
        {
          "name": "Складываемые задние",
          "value": "40/60",
          "weight": 1
        },
        {
          "name": "Вентиляция передних сидений\n",
          "value": "нет",
          "weight": 1
        }
      ]
    },
    {
      "name": "X-TRAIL LE Top",
      "specs": [
        {
          "name": "name",
          "value": "X-TRAIL LE Top",
          "weight": 1
        },
        {
          "name": "цена",
          "value": "27 524 ",
          "weight": 1
        },
        {
          "name": "Расход",
          "value": "9.4/6.4",
          "weight": 1
        },
        {
          "name": "Объём",
          "value": "2,0 (144)",
          "weight": 1
        },
        {
          "name": "КПП",
          "value": "Вариатор",
          "weight": 1
        },
        {
          "name": "Привод",
          "value": "Полный подключаемый",
          "weight": 1
        },
        {
          "name": "Длина",
          "value": "4640",
          "weight": 1
        },
        {
          "name": "Фары",
          "value": "светодиодные\nс автоматической коррекцией\nОмыватель фар",
          "weight": 1
        },
        {
          "name": "Диски",
          "value": "R18 легкосплавные",
          "weight": 1
        },
        {
          "name": "Безключевой доступ",
          "value": "Система дистанционной \nидентификации ключей",
          "weight": 1
        },
        {
          "name": "Запуск двигателя с кнопки",
          "value": "да",
          "weight": 1
        },
        {
          "name": "Подушки безопасности",
          "value": "фронтальные  (2)\t\nбоковые  (2)\t\nбоковые шторки  (4)",
          "weight": 1
        },
        {
          "name": "Климат",
          "value": "двухзонный",
          "weight": 1
        },
        {
          "name": "камера заднего вида ",
          "value": "кругового",
          "weight": 1
        },
        {
          "name": "-контроля давления воздуха в шинах (TMPS)        ",
          "value": "нет",
          "weight": 1
        },
        {
          "name": " обивка сидений ",
          "value": "кожей",
          "weight": 1
        },
        {
          "name": "Регулировка сиденья водителя  ",
          "value": "с электроприводом\nс поясничного подпора",
          "weight": 1
        },
        {
          "name": "подогрев передних сидений, \n",
          "value": "да",
          "weight": 1
        },
        {
          "name": "Подогрев рулевого колеса\n",
          "value": "нет",
          "weight": 1
        },
        {
          "name": "подогрев задних сидений",
          "value": "нет",
          "weight": 1
        },
        {
          "name": "Подогрев лобового стекла ",
          "value": "обогревом",
          "weight": 1
        },
        {
          "name": "Дисплей передний\t",
          "value": "7 дюймов, сенсорный",
          "weight": 1
        },
        {
          "name": "Навигационная система 7',",
          "value": "да",
          "weight": 1
        },
        {
          "name": "Складываемые задние",
          "value": "да",
          "weight": 1
        },
        {
          "name": "Вентиляция передних сидений\n",
          "value": "нет",
          "weight": 1
        }
      ]
    },
    {
      "name": "SPORTAGE-NEW Exclusive",
      "specs": [
        {
          "name": "name",
          "value": "SPORTAGE-NEW Exclusive",
          "weight": 1
        },
        {
          "name": "цена",
          "value": "29 300",
          "weight": 1
        },
        {
          "name": "скидка",
          "value": "3600",
          "weight": 1
        },
        {
          "name": "гарантия",
          "value": "5 лет",
          "weight": 1
        },
        {
          "name": "Расход",
          "value": "11.2 / \t6.7",
          "weight": 1
        },
        {
          "name": "Объём",
          "value": "2,0i (155 л.с.) ",
          "weight": 1
        },
        {
          "name": "КПП",
          "value": "6АТ\n",
          "weight": 1
        },
        {
          "name": "Привод",
          "value": "Полный подключаемый",
          "weight": 1
        },
        {
          "name": "Длина",
          "value": "4485",
          "weight": 1
        },
        {
          "name": "Фары",
          "value": "светодиодные",
          "weight": 1
        },
        {
          "name": "Диски",
          "value": "R17 легкосплавные",
          "weight": 1
        },
        {
          "name": "Безключевой доступ",
          "value": "да",
          "weight": 1
        },
        {
          "name": "Запуск двигателя с кнопки",
          "value": "да",
          "weight": 1
        },
        {
          "name": "Подушки безопасности",
          "value": "Передние подушки безопасности с функцией отключения подушки безопасности пассажира\nБоковые подушки безопасности и\n подушки безопасности занавесочного типа",
          "weight": 1
        },
        {
          "name": "Климат",
          "value": "Двузонный",
          "weight": 1
        },
        {
          "name": "камера заднего вида ",
          "value": "задняя",
          "weight": 1
        },
        {
          "name": "-контроля давления воздуха в шинах (TMPS)        ",
          "value": "да",
          "weight": 1
        },
        {
          "name": " обивка сидений ",
          "value": "Комбинированная",
          "weight": 1
        },
        {
          "name": "Регулировка сиденья водителя  ",
          "value": "да",
          "weight": 1
        },
        {
          "name": "подогрев передних сидений, \n",
          "value": "Трехступенчатый",
          "weight": 1
        },
        {
          "name": "Подогрев рулевого колеса\n",
          "value": "да",
          "weight": 1
        },
        {
          "name": "подогрев задних сидений",
          "value": "да",
          "weight": 1
        },
        {
          "name": "Подогрев лобового стекла ",
          "value": "в районе стоянки щеток",
          "weight": 1
        },
        {
          "name": "Дисплей передний\t",
          "value": "да",
          "weight": 1
        },
        {
          "name": "Навигационная система 7',",
          "value": "да",
          "weight": 1
        },
        {
          "name": "Складываемые задние",
          "value": "нет",
          "weight": 1
        },
        {
          "name": "Вентиляция передних сидений\n",
          "value": "да",
          "weight": 1
        }
      ]
    }
  ],
  "criteria": [
    {
      "name": "цена",
      "weight": 9,
      "meta": "Finance"
    },
    {
      "name": "скидка",
      "weight": 9,
      "meta": "Finance"
    },
    {
      "name": "гарантия",
      "weight": 9,
      "meta": "кредит"
    },
    {
      "name": "Расход",
      "weight": 9,
      "meta": "Технические параметры"
    },
    {
      "name": "Объём",
      "weight": 9,
      "meta": "Технические параметры"
    },
    {
      "name": "КПП",
      "weight": 9,
      "meta": "Технические параметры"
    },
    {
      "name": "Привод",
      "weight": 9,
      "meta": "Технические параметры"
    },
    {
      "name": "Длина",
      "weight": 9,
      "meta": "Технические параметры"
    },
    {
      "name": "Фары",
      "weight": 9,
      "meta": "Комплектация"
    },
    {
      "name": "Диски",
      "weight": 9,
      "meta": "Комплектация"
    },
    {
      "name": "Безключевой доступ",
      "weight": 9,
      "meta": "Комплектация"
    },
    {
      "name": "Запуск двигателя с кнопки",
      "weight": 9,
      "meta": "Комплектация"
    },
    {
      "name": "Подушки безопасности",
      "weight": 9,
      "meta": "Комплектация"
    },
    {
      "name": "Круиз-контроль  ",
      "weight": 9,
      "meta": "Комплектация"
    },
    {
      "name": "Климат",
      "weight": 9,
      "meta": "Комплектация"
    },
    {
      "name": "камера заднего вида ",
      "weight": 9,
      "meta": "Комплектация"
    },
    {
      "name": "-контроля давления воздуха в шинах (TMPS)        ",
      "weight": 9,
      "meta": "Комплектация"
    },
    {
      "name": " обивка сидений ",
      "weight": 9,
      "meta": "Комфорт"
    },
    {
      "name": "Регулировка сиденья водителя  ",
      "weight": 9,
      "meta": "Комфорт"
    },
    {
      "name": "подогрев передних сидений, \n",
      "weight": 9,
      "meta": "Подогрев"
    },
    {
      "name": "Подогрев рулевого колеса\n",
      "weight": 9,
      "meta": "Подогрев"
    },
    {
      "name": "подогрев задних сидений",
      "weight": 9,
      "meta": "Подогрев"
    },
    {
      "name": "Подогрев лобового стекла ",
      "weight": 9,
      "meta": "Подогрев"
    },
    {
      "name": "Дисплей передний\t",
      "weight": 9,
      "meta": "Мультимедиа"
    },
    {
      "name": "Навигационная система 7',",
      "weight": 9,
      "meta": "Мультимедиа"
    },
    {
      "name": "Складываемые задние",
      "weight": 9,
      "meta": "вспомогательное"
    },
    {
      "name": "Вентиляция передних сидений\n",
      "weight": 9,
      "meta": "вспомогательное"
    }
  ]
}
